[
{
"school_email":"mtohmaz@ncsu.edu",
"school_id":1,
"password":"password1",
"first_name":"Mahmoud",
"last_name":"Tohmaz",
"gender":"male",
"first_language":"English",
"nationality":"Syrian",
"dietary_restriction":"Pork",
"interest_expertise":"software",
"club_participated":"MSA",
"favorite_class":"Automata",
"recent_concern":"grades",
"something_want_to_try_in_future":"spearfishing",
"sleep_time":2300,
"wakeup_time":630,
"id":0
},
{
"school_email":"sesterli@usc.edu",
"school_id":2,
"password":"password2",
"first_name":"Sherman",
"last_name":"Esterline",
"gender":"male",
"first_language":"English",
"nationality":"British",
"dietary_restriction":"None",
"interest_expertise":"Art",
"club_participated":"Chess Club",
"favorite_class":"Art History",
"recent_concern":"tuition cost",
"something_want_to_try_in_future":"skydiving",
"sleep_time":2225,
"wakeup_time":745,
"id":1
},
{
"school_email":"nzorn@ncsu.edu",
"school_id":1,
"password":"password3",
"first_name":"Nedra",
"last_name":"Zorn",
"gender":"female",
"first_language":"Arabic",
"nationality":"Egyption",
"dietary_restriction":"Pork",
"interest_expertise":"History",
"club_participated":"None",
"favorite_class":"Ancient History",
"recent_concern":"finding roommate",
"something_want_to_try_in_future":"jet skiing",
"sleep_time":2100,
"wakeup_time":700,
"id":2
},
{
"school_email":"adevaul@cmu.edu",
"school_id":3,
"password":"password4",
"first_name":"Angila",
"last_name":"Devaul",
"gender":"female",
"first_language":"German",
"nationality":"Germany",
"dietary_restriction":"Vegetarian",
"interest_expertise":"hardware",
"club_participated":"IEEE",
"favorite_class":"Embedded Systems",
"recent_concern":"Robotics Competition",
"something_want_to_try_in_future":"Scuba Diving",
"sleep_time":2245,
"wakeup_time":816,
"id":3
},
{
"school_email":"cwelcher@ncsu.edu",
"school_id":1,
"password":"password5",
"first_name":"Ciera",
"last_name":"Welcher",
"gender":"female",
"first_language":"English",
"nationality":"American",
"dietary_restriction":"None",
"interest_expertise":"Chemistry",
"club_participated":"None",
"favorite_class":"Organic Chemistry",
"recent_concern":"homework load",
"something_want_to_try_in_future":"Kayaking",
"sleep_time":2355,
"wakeup_time":1100,
"id":4
},
{
"school_email":"jcroll@ncsu.edu",
"school_id":1,
"password":"password6",
"first_name":"Janis",
"last_name":"Croll",
"gender":"female",
"first_language":"English",
"nationality":"American",
"dietary_restriction":"Vegan",
"interest_expertise":"Nuclear Engineering",
"club_participated":"None",
"favorite_class":"Economics",
"recent_concern":"studying",
"something_want_to_try_in_future":"Defy Gravity",
"sleep_time":2310,
"wakeup_time":730,
"id":5
},
{
"school_email":"agauger@berkeley.edu",
"school_id":4,
"password":"password7",
"first_name":"Aldo",
"last_name":"Gauger",
"gender":"male",
"first_language":"Spanish",
"nationality":"Mexican",
"dietary_restriction":"None",
"interest_expertise":"Psychology",
"club_participated":"Boxing Club",
"favorite_class":"Intro to Psychology",
"recent_concern":"studying",
"something_want_to_try_in_future":"spearfishing",
"sleep_time":2150,
"wakeup_time":730,
"id":6
},
{
"school_email":"ejune@ncsu.edu",
"school_id":1,
"password":"password8",
"first_name":"Everette",
"last_name":"June",
"gender":"male",
"first_language":"English",
"nationality":"American",
"dietary_restriction":"None",
"interest_expertise":"software",
"club_participated":"Boxing Club",
"favorite_class":"Operating Systems",
"recent_concern":"grades",
"something_want_to_try_in_future":"Kayaking",
"sleep_time":2240,
"wakeup_time":700,
"id":7
},
{
"school_email":"lrawling@ncsu.edu",
"school_id":1,
"password":"password9",
"first_name":"Laurel",
"last_name":"Rawlings",
"gender":"female",
"first_language":"English",
"nationality":"American",
"dietary_restriction":"None",
"interest_expertise":"Business",
"club_participated":"Mock UN",
"favorite_class":"Economics",
"recent_concern":"studying",
"something_want_to_try_in_future":"jet skiing",
"sleep_time":2150,
"wakeup_time":600,
"id":8
},
{
"school_email":"ltelford@ncsu.edu",
"school_id":1,
"password":"password10",
"first_name":"Lavona",
"last_name":"Telford",
"gender":"female",
"first_language":"French",
"nationality":"French",
"dietary_restriction":"None",
"interest_expertise":"Economics",
"club_participated":"Mock UN",
"favorite_class":"Intermediate Business",
"recent_concern":"grades",
"something_want_to_try_in_future":"snowboarding",
"sleep_time":2400,
"wakeup_time":730,
"id":9
},
{
"school_email":"jmurdoch@duke.edu",
"school_id":5,
"password":"password11",
"first_name":"Joel",
"last_name":"Murdoch",
"gender":"male",
"first_language":"English",
"nationality":"American",
"dietary_restriction":"None",
"interest_expertise":"software",
"club_participated":"None",
"favorite_class":"Software Engineering",
"recent_concern":"grades",
"something_want_to_try_in_future":"Scuba Diving",
"sleep_time":2300,
"wakeup_time":630,
"id":10
},
{
"school_email":"malfred@ncsu.edu",
"school_id":1,
"password":"password12",
"first_name":"Marceline",
"last_name":"Alfred",
"gender":"female",
"first_language":"English",
"nationality":"American",
"dietary_restriction":"Vegetarian",
"interest_expertise":"Economics",
"club_participated":"Boxing Club",
"favorite_class":"Intermediate Economics",
"recent_concern":"studying",
"something_want_to_try_in_future":"snowboarding",
"sleep_time":2200,
"wakeup_time":730,
"id":11
},
{
"school_email":"icienfue@ncsu.edu",
"school_id":1,
"password":"password13",
"first_name":"Irina",
"last_name":"Cienfuegos",
"gender":"female",
"first_language":"Spanish",
"nationality":"Mexican",
"dietary_restriction":"None",
"interest_expertise":"software",
"club_participated":"MSA",
"favorite_class":"Building Game AI",
"recent_concern":"grades",
"something_want_to_try_in_future":"jet skiing",
"sleep_time":2200,
"wakeup_time":630,
"id":12
},
{
"school_email":"tperras@yale.edu",
"school_id":6,
"password":"password14",
"first_name":"Tamatha",
"last_name":"Perras",
"gender":"female",
"first_language":"Spanish",
"nationality":"Spanish",
"dietary_restriction":"None",
"interest_expertise":"History",
"club_participated":"None",
"favorite_class":"None",
"recent_concern":"None",
"something_want_to_try_in_future":"skydiving",
"sleep_time":2330,
"wakeup_time":1040,
"id":13
},
{
"school_email":"aburrage@ncsu.edu",
"school_id":1,
"password":"password15",
"first_name":"Abbie",
"last_name":"Burrage",
"gender":"female",
"first_language":"English",
"nationality":"American",
"dietary_restriction":"None",
"interest_expertise":"software",
"club_participated":"Boxing Club",
"favorite_class":"Software Engineering",
"recent_concern":"studying",
"something_want_to_try_in_future":"skiing",
"sleep_time":2250,
"wakeup_time":1000,
"id":14
},
{
"school_email":"rhazan@nd.edu",
"school_id":7,
"password":"password16",
"first_name":"Roxana",
"last_name":"Hazan",
"gender":"Female",
"first_language":"Portugese",
"nationality":"Brazilian",
"dietary_restriction":"Lactose Intolerant",
"interest_expertise":"Economics",
"club_participated":"SGN",
"favorite_class":"Intermediate Economics",
"recent_concern":"studying",
"something_want_to_try_in_future":"spearfishing",
"sleep_time":2300,
"wakeup_time":630,
"id":15
},
{
"school_email":"sburrowe@uw.edu",
"school_id":8,
"password":"password17",
"first_name":"Santa",
"last_name":"Burrowes",
"gender":"female",
"first_language":"Italian",
"nationality":"Italian",
"dietary_restriction":"Vegan",
"interest_expertise":"English",
"club_participated":"None",
"favorite_class":"Intro to English",
"recent_concern":"studying",
"something_want_to_try_in_future":"sky diving",
"sleep_time":2300,
"wakeup_time":630,
"id":16
},
{
"school_email":"jkratzer@ncsu.edu",
"school_id":1,
"password":"password18",
"first_name":"Jayna",
"last_name":"Kratzer",
"gender":"female",
"first_language":"Dutch",
"nationality":"Netherlands",
"dietary_restriction":"Vegetarian",
"interest_expertise":"software",
"club_participated":"WICS",
"favorite_class":"C Programming",
"recent_concern":"grades",
"something_want_to_try_in_future":"Scuba Diving",
"sleep_time":2300,
"wakeup_time":630,
"id":17
},
{
"school_email":"lzeck@ncsu.edu",
"school_id":1,
"password":"password19",
"first_name":"Lia",
"last_name":"Zeck",
"gender":"female",
"first_language":"English",
"nationality":"American",
"dietary_restriction":"None",
"interest_expertise":"Economics",
"club_participated":"None",
"favorite_class":"Into to Economics",
"recent_concern":"grades",
"something_want_to_try_in_future":"sky diving",
"sleep_time":2400,
"wakeup_time":1120,
"id":18
},
{
"school_email":"scapron@unc.edu",
"school_id":9,
"password":"password20",
"first_name":"Shanon",
"last_name":"Capron",
"gender":"female",
"first_language":"English",
"nationality":"Australian",
"dietary_restriction":"None",
"interest_expertise":"software",
"club_participated":"WICS",
"favorite_class":"Automata",
"recent_concern":"grades",
"something_want_to_try_in_future":"Racing",
"sleep_time":2250,
"wakeup_time":700,
"id":19
},
{
"school_email":"avince@ncsu.edu",
"school_id":1,
"password":"password21",
"first_name":"Aileen",
"last_name":"Vince",
"gender":"female",
"first_language":"English",
"nationality":"American",
"dietary_restriction":"Vegan",
"interest_expertise":"software",
"club_participated":"MSA",
"favorite_class":"Software Engineering",
"recent_concern":"studying",
"something_want_to_try_in_future":"spearfishing",
"sleep_time":2300,
"wakeup_time":630,
"id":20
},
{
"school_email":"alavery@uncc.edu",
"school_id":10,
"password":"password22",
"first_name":"Alishia",
"last_name":"Lavery",
"gender":"female",
"first_language":"English",
"nationality":"American",
"dietary_restriction":"Vegetarian",
"interest_expertise":"History",
"club_participated":"Mock UN",
"favorite_class":"Modern American History",
"recent_concern":"school",
"something_want_to_try_in_future":"sky diving",
"sleep_time":2350,
"wakeup_time":730,
"id":21
},
{
"school_email":"mdepew@ncsu.edu",
"school_id":1,
"password":"password23",
"first_name":"Margarete",
"last_name":"Depew",
"gender":"female",
"first_language":"English",
"nationality":"American",
"dietary_restriction":"Lactose Intolerant",
"interest_expertise":"software",
"club_participated":"WICS",
"favorite_class":"Automata",
"recent_concern":"grades",
"something_want_to_try_in_future":"Scuba Diving",
"sleep_time":2400,
"wakeup_time":730,
"id":22
},
{
"school_email":"ddestefa@uncg.edu",
"school_id":11,
"password":"password24",
"first_name":"Dacia",
"last_name":"Destefano",
"gender":"female",
"first_language":"Spanish",
"nationality":"Mexican",
"dietary_restriction":"Lactose Intolerant",
"interest_expertise":"software",
"club_participated":"WICS",
"favorite_class":"Automata",
"recent_concern":"grades",
"something_want_to_try_in_future":"sky diving",
"sleep_time":2200,
"wakeup_time":740,
"id":23
},
{
"school_email":"lpujol@ncsu.edu",
"school_id":1,
"password":"password25",
"first_name":"Lynwood",
"last_name":"Pujol",
"gender":"male",
"first_language":"English",
"nationality":"American",
"dietary_restriction":"None",
"interest_expertise":"English",
"club_participated":"None",
"favorite_class":"Shakespear",
"recent_concern":"grades",
"something_want_to_try_in_future":"Scuba Diving",
"sleep_time":2340,
"wakeup_time":941,
"id":24
},
{
"school_email":"lcomerfo@ncsu.edu",
"school_id":1,
"password":"password26",
"first_name":"Lawerence",
"last_name":"Comerford",
"gender":"male",
"first_language":"English",
"nationality":"American",
"dietary_restriction":"Lactose Intolerant",
"interest_expertise":"software",
"club_participated":"None",
"favorite_class":"Automata",
"recent_concern":"grades",
"something_want_to_try_in_future":"go carting",
"sleep_time":2300,
"wakeup_time":630,
"id":25
},
{
"school_email":"cdewalt@usc.edu",
"school_id":2,
"password":"password27",
"first_name":"Conception",
"last_name":"Dewalt",
"gender":"female",
"first_language":"Mandarin",
"nationality":"Chinese",
"dietary_restriction":"Pork",
"interest_expertise":"software",
"club_participated":"MSA",
"favorite_class":"Automata",
"recent_concern":"grades",
"something_want_to_try_in_future":"spearfishing",
"sleep_time":2300,
"wakeup_time":630,
"id":26
},
{
"school_email":"agatewoo@ncsu.edu",
"school_id":1,
"password":"password28",
"first_name":"Angle",
"last_name":"Gatewood",
"gender":"female",
"first_language":"English",
"nationality":"American",
"dietary_restriction":"None",
"interest_expertise":"software",
"club_participated":"WICS",
"favorite_class":"Automata",
"recent_concern":"grades",
"something_want_to_try_in_future":"parasailing",
"sleep_time":2300,
"wakeup_time":630,
"id":27
},
{
"school_email":"lsiler@cmu.edu",
"school_id":3,
"password":"password29",
"first_name":"Lien",
"last_name":"Siler",
"gender":"female",
"first_language":"English",
"nationality":"American",
"dietary_restriction":"None",
"interest_expertise":"software",
"club_participated":"WICS",
"favorite_class":"Software Engineering",
"recent_concern":"grades",
"something_want_to_try_in_future":"jet skiing",
"sleep_time":2140,
"wakeup_time":730,
"id":28
},
{
"school_email":"cmcaninc@ncsu.edu",
"school_id":1,
"password":"password30",
"first_name":"Mahmoud",
"last_name":"Tohmaz",
"gender":"female",
"first_language":"English",
"nationality":"American",
"dietary_restriction":"None",
"interest_expertise":"software",
"club_participated":"WICS",
"favorite_class":"Operating Systems",
"recent_concern":"studying",
"something_want_to_try_in_future":"sky diving",
"sleep_time":2300,
"wakeup_time":630,
"id":29
},
{
"school_email":"dsinglet@berkeley.edu",
"school_id":4,
"password":"password31",
"first_name":"Delta",
"last_name":"Singleterry",
"gender":"female",
"first_language":"Hindi",
"nationality":"Indian",
"dietary_restriction":"Lactose Intolerant",
"interest_expertise":"software",
"club_participated":"WICS",
"favorite_class":"Automata",
"recent_concern":"grades",
"something_want_to_try_in_future":"spearfishing",
"sleep_time":2300,
"wakeup_time":730,
"id":30
},
{
"school_email":"pandra@duke.edu",
"school_id":5,
"password":"password32",
"first_name":"Pranav",
"last_name":"Andra",
"gender":"male",
"first_language":"Bengali",
"nationality":"Indian",
"dietary_restriction":"Vegetarian",
"interest_expertise":"software",
"club_participated":"None",
"favorite_class":"Software Engineering",
"recent_concern":"grades",
"something_want_to_try_in_future":"travelling",
"sleep_time":2300,
"wakeup_time":630,
"id":31
},
{
"school_email":"okhan@ncsu.edu",
"school_id":1,
"password":"password33",
"first_name":"Orenda",
"last_name":"Khan",
"gender":"female",
"first_language":"Urdu",
"nationality":"India",
"dietary_restriction":"Vegetarian",
"interest_expertise":"software",
"club_participated":"None",
"favorite_class":"Automata",
"recent_concern":"grades",
"something_want_to_try_in_future":"spearfishing",
"sleep_time":2320,
"wakeup_time":730,
"id":32
},
{
"school_email":"kbasak@yale.edu",
"school_id":6,
"password":"password34",
"first_name":"Kaya",
"last_name":"Basak",
"gender":"female",
"first_language":"Hindi",
"nationality":"Indian",
"dietary_restriction":"None",
"interest_expertise":"software",
"club_participated":"WICS",
"favorite_class":"Software Engineering",
"recent_concern":"grades",
"something_want_to_try_in_future":"spearfishing",
"sleep_time":2200,
"wakeup_time":630,
"id":33
},
{
"school_email":"hyu@nd.edu",
"school_id":7,
"password":"password35",
"first_name":"Hiroki",
"last_name":"Yu",
"gender":"male",
"first_language":"Japanese",
"nationality":"Japan",
"dietary_restriction":"None",
"interest_expertise":"software",
"club_participated":"None",
"favorite_class":"Automata",
"recent_concern":"grades",
"something_want_to_try_in_future":"Scuba Diving",
"sleep_time":2300,
"wakeup_time":630,
"id":34
},
{
"school_email":"ayen@uw.edu",
"school_id":8,
"password":"password36",
"first_name":"Ayumi",
"last_name":"Yen",
"gender":"female",
"first_language":"Japanese",
"nationality":"Japan",
"dietary_restriction":"None",
"interest_expertise":"software",
"club_participated":"WICS",
"favorite_class":"Software Engineering",
"recent_concern":"grades",
"something_want_to_try_in_future":"Sailing",
"sleep_time":2250,
"wakeup_time":830,
"id":35
},
{
"school_email":"rkento@unc.edu",
"school_id":9,
"password":"password37",
"first_name":"Rika",
"last_name":"Kento",
"gender":"female",
"first_language":"Japenese",
"nationality":"Japan",
"dietary_restriction":"Lactose Intolerant",
"interest_expertise":"software",
"club_participated":"WICS",
"favorite_class":"Operating Systems",
"recent_concern":"studying",
"something_want_to_try_in_future":"spearfishing",
"sleep_time":2300,
"wakeup_time":830,
"id":36
},
{
"school_email":"mthomas@uncc.edu",
"school_id":10,
"password":"password38",
"first_name":"Mark",
"last_name":"Thomas",
"gender":"male",
"first_language":"English",
"nationality":"American",
"dietary_restriction":"None",
"interest_expertise":"software",
"club_participated":"None",
"favorite_class":"Automata",
"recent_concern":"grades",
"something_want_to_try_in_future":"Sailing",
"sleep_time":2300,
"wakeup_time":630,
"id":37
},
{
"school_email":"jwinston@uncg.edu",
"school_id":11,
"password":"password39",
"first_name":"John",
"last_name":"Winston",
"gender":"male",
"first_language":"English",
"nationality":"American",
"dietary_restriction":"Vegetarian",
"interest_expertise":"software",
"club_participated":"None",
"favorite_class":"Software Engineering",
"recent_concern":"grades",
"something_want_to_try_in_future":"go carting",
"sleep_time":2400,
"wakeup_time":600,
"id":38
},
{
"school_email":"emarcus@ncsu.edu",
"school_id":1,
"password":"password40",
"first_name":"Eddie",
"last_name":"Marcus",
"gender":"male",
"first_language":"English",
"nationality":"American",
"dietary_restriction":"None",
"interest_expertise":"software",
"club_participated":"None",
"favorite_class":"Software Engineering",
"recent_concern":"grades",
"something_want_to_try_in_future":"go carting",
"sleep_time":2100,
"wakeup_time":600,
"id":39
}
]